aws_sg_backup/__init__.py
aws_sg_backup/security_group.py
aws_sg_backup-0.1.0.dist-info/WHEEL
aws_sg_backup-0.1.0.dist-info/METADATA
aws_sg_backup-0.1.0.dist-info/RECORD
