Metadata-Version: 2.1
Name: aws-sg-backup
Version: 0.1.0
Summary: Backup and restore AWS security groups as local files or to S3
Author: Vassili Gorshkov
Author-email: vassili.gorshkov@atlasgurus.com
Requires-Python: >=3.7,<4.0
Classifier: Programming Language :: Python :: 3
Classifier: Programming Language :: Python :: 3.10
Classifier: Programming Language :: Python :: 3.7
Classifier: Programming Language :: Python :: 3.8
Classifier: Programming Language :: Python :: 3.9
Requires-Dist: boto3 (>=1.26.25,<2.0.0)
